{
  "isSuccess": true,
  "data": {
    "dailyMetrics": [
      {
        "date": "2025-12-28",
        "metrics": [
          {
            "metricName": "Sleep",
            "unit": "Hours",
            "metricDefinitionId": 1,
            "date": "2025-12-28",
            "metricValue": 8
          },
          {
            "metricName": "Water",
            "unit": "Litres",
            "metricDefinitionId": 2,
            "date": "2025-12-28",
            "metricValue": 3
          }
        ]
      }
    ],
    "activities": [
      {
        "activityId": 1,
        "activityName": "Excercise",
        "activityDetails": "Do 30 min",
        "datesData": [
          {
            "date": "2025-12-28",
            "isDone": true
          }
        ]
      },
      {
        "activityId": 2,
        "activityName": "Reading",
        "activityDetails": "Read 5 pages",
        "datesData": [
          {
            "date": "2025-12-28",
            "isDone": false
          }
        ]
      }
    ]
  },
  "errorCode": null,
  "errorMessage": null
}